postgres_fixture/__init__.py
postgres_fixture/analysis.py
postgres_fixture/db.py
postgres_fixture/postgres_fixture.py
postgres_fixture-0.1.0.dist-info/entry_points.txt
postgres_fixture-0.1.0.dist-info/WHEEL
postgres_fixture-0.1.0.dist-info/METADATA
postgres_fixture-0.1.0.dist-info/RECORD
